[
  {
    "AP": 0.3977859955147547,
    "AP_S": 0.11901583107671375,
    "AP_M": 0.3871172603287889,
    "AP_L": 0.27595757911828395,
    "n_gt_small": 13246,
    "n_gt_medium": 4890,
    "n_gt_large": 506,
    "n_gt_total": 18642,
    "attack": "Clean",
    "attack_type": "none",
    "eps": 0,
    "time_s": 17.7,
    "n_dets": 76989
  },
  {
    "AP": 0.3970596904884633,
    "AP_S": 0.11873395748430919,
    "AP_M": 0.3875412804704421,
    "AP_L": 0.2555353409068346,
    "n_gt_small": 13246,
    "n_gt_medium": 4890,
    "n_gt_large": 506,
    "n_gt_total": 18642,
    "attack": "FGSM_2",
    "attack_type": "fgsm",
    "eps": 0.00784313725490196,
    "time_s": 21.2,
    "n_dets": 76490
  },
  {
    "AP": 0.3964941810283509,
    "AP_S": 0.11832567484868738,
    "AP_M": 0.3919401486624459,
    "AP_L": 0.2589753124844483,
    "n_gt_small": 13246,
    "n_gt_medium": 4890,
    "n_gt_large": 506,
    "n_gt_total": 18642,
    "attack": "FGSM_4",
    "attack_type": "fgsm",
    "eps": 0.01568627450980392,
    "time_s": 21.1,
    "n_dets": 76064
  },
  {
    "AP": 0.38712154526409354,
    "AP_S": 0.11518193938893061,
    "AP_M": 0.38350755668154773,
    "AP_L": 0.2452814168391603,
    "n_gt_small": 13246,
    "n_gt_medium": 4890,
    "n_gt_large": 506,
    "n_gt_total": 18642,
    "attack": "FGSM_8",
    "attack_type": "fgsm",
    "eps": 0.03137254901960784,
    "time_s": 21.2,
    "n_dets": 76470
  },
  {
    "AP": 0.33998384084256444,
    "AP_S": 0.09331207591388421,
    "AP_M": 0.3465739442658752,
    "AP_L": 0.21229679193634213,
    "n_gt_small": 13246,
    "n_gt_medium": 4890,
    "n_gt_large": 506,
    "n_gt_total": 18642,
    "attack": "FGSM_16",
    "attack_type": "fgsm",
    "eps": 0.06274509803921569,
    "time_s": 21.7,
    "n_dets": 78339
  },
  {
    "AP": 0.3948266456130353,
    "AP_S": 0.11736924304644995,
    "AP_M": 0.39093488521048203,
    "AP_L": 0.264422306811652,
    "n_gt_small": 13246,
    "n_gt_medium": 4890,
    "n_gt_large": 506,
    "n_gt_total": 18642,
    "attack": "PGD_8",
    "attack_type": "pgd",
    "eps": 0.03137254901960784,
    "time_s": 21.3,
    "n_dets": 75859
  },
  {
    "AP": 0.38195658080347045,
    "AP_S": 0.11308141828963789,
    "AP_M": 0.3788065936743132,
    "AP_L": 0.23257545666413196,
    "n_gt_small": 13246,
    "n_gt_medium": 4890,
    "n_gt_large": 506,
    "n_gt_total": 18642,
    "attack": "PGD_16",
    "attack_type": "pgd",
    "eps": 0.06274509803921569,
    "time_s": 21.4,
    "n_dets": 76202
  }
]